pysiaalarm/__init__.py
pysiaalarm/account.py
pysiaalarm/base_client.py
pysiaalarm/base_server.py
pysiaalarm/const.py
pysiaalarm/errors.py
pysiaalarm/event.py
pysiaalarm/py.typed
pysiaalarm/aio/__init__.py
pysiaalarm/aio/client.py
pysiaalarm/aio/server.py
pysiaalarm/data/__init__.py
pysiaalarm/data/adm_mapping.py
pysiaalarm/data/data.py
pysiaalarm/data/sia_codes.py
pysiaalarm/data/xdata.py
pysiaalarm/sync/__init__.py
pysiaalarm/sync/client.py
pysiaalarm/sync/handler.py
pysiaalarm/sync/server.py
pysiaalarm/utils/__init__.py
pysiaalarm/utils/counter.py
pysiaalarm/utils/enums.py
pysiaalarm/utils/regexes.py
pysiaalarmajax-4.0.1.dist-info/licenses/AUTHORS.rst
pysiaalarmajax-4.0.1.dist-info/licenses/LICENSE.txt
pysiaalarmajax-4.0.1.dist-info/METADATA
pysiaalarmajax-4.0.1.dist-info/WHEEL
pysiaalarmajax-4.0.1.dist-info/top_level.txt
pysiaalarmajax-4.0.1.dist-info/RECORD
